{"number":360,"date":"1994-07-29","issue":"土地登記代理人管理辦法就請領證書資格之限制規定違憲？","holding":"土地法第三十七條之一第二項係依憲法第八十六條第二款而制定，與憲法並無牴觸，業經本院釋字第三五二號解釋釋示在案。內政部於中華民國七十九年六月二十九日發布之土地登記專業代理人管理辦法，則係依據上開法條第四項授權訂定，其第四條：「合於左列資格之一者，得請領專業代理人證書：一、經專業代理人考試或檢覈及格者。二、領有直轄市、縣（市）政府核發土地代書人登記合格證明者。三、領有直轄市、縣（市）政府核發代理他人申辦土地登記案件專業人員登記卡者」之規定，並未逾越法律授權範圍，與憲法亦無牴觸。","reasoning":"依憲法第二十三條之規定，國家對於人民之自由及權利有所限制，固應以法律定之。惟法律對於有關人民權利義務之事項，不能鉅細靡遺，一律加以規定，其屬於細節性、技術性者，法律自得授權主管機關以命令定之，俾便法律之實施。行政機關基於此種授權發布之命令，其內容未逾越授權範圍，並符合授權之目的者，自為憲法之所許。\n土地法第三十七條之一第二項規定：「土地登記專業代理人，應經土地登記專業代理人考試或檢覈及格。但在本法修正施行前，已從事土地登記專業代理業務，並曾領有政府發給土地代書人登記合格證明或代理他人申辦土地登記案件專業人員登記卡者，得繼續執業，未領有土地代書人登記合格證明或登記卡者，得繼續執業五年」，係依憲法第八十六條第二款而制定，與憲法並無牴觸，業經本院釋字第三五二號解釋釋示在案。內政部於中華民國七十九年六月二十九日發布之土地登記專業代理人管理辦法，則係依據上開法條第四項授權訂定，其第四條：「合於左列資格之一者，得請領專業代理人證書：一、經專業代理人考試或檢覈及格者。二、領有直轄市、縣（市）政府核發土地代書人登記合格證明者。三、領有直轄市、縣（市）政府核發代理他人申辦土地登記案件專業人員登記卡者」之規定，並未逾越法律授權範圍，與憲法亦無牴觸。","related_articles":["憲法第23條(36.01.01)","憲法第86條第2款(36.01.01)","司法院釋字第352號解釋","土地法第37條之1第2項、第4項(78.12.29)","土地登記專業代理人管理辦法第4條（79.6.29發布）(79.06.29)"],"related_annexes":true}